higher_institutions_ng/Nigerian Higher Institutions.json
higher_institutions_ng/__init__.py
higher_institutions_ng/main.py
higher_institutions_ng-0.0.3.dist-info/LICENSE
higher_institutions_ng-0.0.3.dist-info/METADATA
higher_institutions_ng-0.0.3.dist-info/WHEEL
higher_institutions_ng-0.0.3.dist-info/top_level.txt
higher_institutions_ng-0.0.3.dist-info/RECORD
