Metadata-Version: 2.1
Name: higher_institutions_ng
Version: 0.0.3
Summary: Information about Nigerian higher institutions.
Home-page: https://github.com/awesomegoodman/higher-institutions-ng/tree/main/pypi
Author: Awesome Goodman
Author-email: goodman.awesome@gmail.com
Keywords: Nigerian School List,Nigerian Schools,Nigerian Colleges,Nigerian Universities,Nigerian Polytechnics,Nigerian Higher Institutions,State,Federal,Nigeria
Classifier: Programming Language :: Python :: 3
Classifier: License :: OSI Approved :: MIT License
Classifier: Intended Audience :: Developers
Classifier: Operating System :: OS Independent
License-File: LICENSE
